aws_glue_container_launcher/__init__.py
aws_glue_container_launcher/_version.py
aws_glue_container_launcher/api.py
aws_glue_container_launcher/docker_command.py
aws_glue_container_launcher/enumeration.py
aws_glue_container_launcher/paths.py
aws_glue_container_launcher/docs/__init__.py
aws_glue_container_launcher/tests/__init__.py
aws_glue_container_launcher/tests/glue.py
aws_glue_container_launcher/tests/helper.py
aws_glue_container_launcher/tests/glue_libs/__init__.py
aws_glue_container_launcher/tests/glue_libs/glue_utils.py
aws_glue_container_launcher/tests/glue_libs/pyspark_utils.py
aws_glue_container_launcher/tests/glue_libs/utils.py
aws_glue_container_launcher/vendor/__init__.py
aws_glue_container_launcher/vendor/pytest_cov_helper.py
aws_glue_container_launcher-0.1.2.dist-info/AUTHORS.rst
aws_glue_container_launcher-0.1.2.dist-info/LICENSE.txt
aws_glue_container_launcher-0.1.2.dist-info/METADATA
aws_glue_container_launcher-0.1.2.dist-info/WHEEL
aws_glue_container_launcher-0.1.2.dist-info/top_level.txt
aws_glue_container_launcher-0.1.2.dist-info/RECORD
